erdos-0.3.1.dist-info/WHEEL
erdos-0.3.1.dist-info/METADATA
erdos-0.3.1.dist-info/top_level.txt
erdos-0.3.1.dist-info/RECORD
erdos/internal.cpython-37m-x86_64-linux-gnu.so
erdos/__init__.py
erdos/profile.py
erdos/internal.cpython-36m-x86_64-linux-gnu.so
erdos/streams.py
erdos/operator.py
erdos/internal.cpython-38-x86_64-linux-gnu.so
erdos/utils.py
erdos/message.py
erdos/internal.cpython-35m-x86_64-linux-gnu.so
erdos/timestamp.py
erdos/operators/__init__.py
erdos/operators/map.py
erdos/operators/window.py
